nonebot_plugin_osubot/__init__.py
nonebot_plugin_osubot/api.py
nonebot_plugin_osubot/beatmap_stats_moder.py
nonebot_plugin_osubot/config.py
nonebot_plugin_osubot/database/__init__.py
nonebot_plugin_osubot/database/models.py
nonebot_plugin_osubot/draw/__init__.py
nonebot_plugin_osubot/draw/bmap.py
nonebot_plugin_osubot/draw/bp.py
nonebot_plugin_osubot/draw/catch_preview.py
nonebot_plugin_osubot/draw/catch_preview_templates/css/style.css
nonebot_plugin_osubot/draw/catch_preview_templates/js/beatmap/beatmap.js
nonebot_plugin_osubot/draw/catch_preview_templates/js/beatmap/hitobject.js
nonebot_plugin_osubot/draw/catch_preview_templates/js/beatmap/point.js
nonebot_plugin_osubot/draw/catch_preview_templates/js/beatmap/scroll.js
nonebot_plugin_osubot/draw/catch_preview_templates/js/beatmap/timingpoint.js
nonebot_plugin_osubot/draw/catch_preview_templates/js/catch/LegacyRandom.js
nonebot_plugin_osubot/draw/catch_preview_templates/js/catch/PalpableCatchHitObject.js
nonebot_plugin_osubot/draw/catch_preview_templates/js/catch/bananashower.js
nonebot_plugin_osubot/draw/catch_preview_templates/js/catch/catch.js
nonebot_plugin_osubot/draw/catch_preview_templates/js/catch/fruit.js
nonebot_plugin_osubot/draw/catch_preview_templates/js/catch/juicestream.js
nonebot_plugin_osubot/draw/catch_preview_templates/js/fakeaudio.js
nonebot_plugin_osubot/draw/catch_preview_templates/js/preview.js
nonebot_plugin_osubot/draw/catch_preview_templates/js/standard/curve/bezier2.js
nonebot_plugin_osubot/draw/catch_preview_templates/js/standard/curve/catmullcurve.js
nonebot_plugin_osubot/draw/catch_preview_templates/js/standard/curve/centripetalcatmullrom.js
nonebot_plugin_osubot/draw/catch_preview_templates/js/standard/curve/circumstancedcircle.js
nonebot_plugin_osubot/draw/catch_preview_templates/js/standard/curve/curve.js
nonebot_plugin_osubot/draw/catch_preview_templates/js/standard/curve/curvetype.js
nonebot_plugin_osubot/draw/catch_preview_templates/js/standard/curve/equaldistancemulticurve.js
nonebot_plugin_osubot-6.27.4.dist-info/WHEEL
nonebot_plugin_osubot-6.27.4.dist-info/METADATA
nonebot_plugin_osubot-6.27.4.dist-info/RECORD
