Metadata-Version: 2.3
Name: nonebot_plugin_osubot
Version: 6.27.4
Summary: OSUbot in NoneBot2
Author: yaowan233
Author-email: yaowan233 <572473053@qq.com>
License: AGPL-3.0
Requires-Dist: nonebot2>=2.3.0
Requires-Dist: pydantic>=1.10.0,!=2.5.0,!=2.5.1,<3.0.0
Requires-Dist: nonebot-plugin-alconna>=0.46.4
Requires-Dist: nonebot-plugin-session~=0.3
Requires-Dist: pillow>=9.2.0
Requires-Dist: expiringdict>=1.2.2
Requires-Dist: nonebot-plugin-apscheduler>=0.4.0
Requires-Dist: tortoise-orm>=0.20.0
Requires-Dist: nonebot-plugin-tortoise-orm>=0.1.4
Requires-Dist: rosu-pp-py==3.1.0
Requires-Dist: reamber>=0.2.1
Requires-Dist: httpx>=0.23.3
Requires-Dist: typing-extensions>=4.11.0
Requires-Dist: matplotlib>=3.7.1
Requires-Dist: nonebot-plugin-htmlrender>=0.3.1
Requires-Dist: nonebot-plugin-waiter>=0.6.1
Requires-Dist: nonebot-adapter-onebot>=2.4.6
Requires-Dist: osu-tools-py>=0.1.2
Requires-Python: >=3.10, <3.14
Project-URL: Homepage, https://github.com/yaowan233/nonebot-plugin-osubot
Project-URL: Repository, https://github.com/yaowan233/nonebot-plugin-osubot
